allanc_sphinx/__init__.py
allanc_sphinx/themes/yeen/layout.html
allanc_sphinx/themes/yeen/theme.conf
allanc_sphinx/themes/yeen/static/yeen.css_t
allanc_sphinx-0.4.dist-info/METADATA
allanc_sphinx-0.4.dist-info/WHEEL
allanc_sphinx-0.4.dist-info/entry_points.txt
allanc_sphinx-0.4.dist-info/top_level.txt
allanc_sphinx-0.4.dist-info/RECORD
