Metadata-Version: 2.1
Name: allanc-sphinx
Version: 0.4
Summary: Sphinx themes used for documentation of my projects.
Home-page: https://github.com/the-allanc/allanc_sphinx
Author: Allan Crooks
Author-email: allan@sixtyten.org
License: MIT
Platform: UNKNOWN
Classifier: License :: OSI Approved :: MIT License
Classifier: Framework :: Sphinx :: Theme
